setup.py
django_admin_image_render/__init__.py
django_admin_image_render/render_image.py
django_admin_image_render.egg-info/PKG-INFO
django_admin_image_render.egg-info/SOURCES.txt
django_admin_image_render.egg-info/dependency_links.txt
django_admin_image_render.egg-info/requires.txt
django_admin_image_render.egg-info/top_level.txt